{
  "name": "Edward Said",
  "slug": "edward-said",
  "book_count": 5,
  "bio": "Edward Wadie Said was a Palestinian and American academic, literary critic, and political activist. As a professor of literature at Columbia University, he was among the founders of post-colonial studies. As a cultural critic, Said is best known for his book Orientalism (1978), a foundational text which critiques the cultural representations that are the bases of Orientalism—how the Western world perceives the Orient. His model of textual analysis transformed the academic discourse of researchers in literary theory, literary criticism, and Middle Eastern studies.",
  "photo_url": "https://upload.wikimedia.org/wikipedia/commons/thumb/f/f8/Edward_Said_and_Daniel_Barenboim_in_Sevilla%2C_2002_%28Said%29.jpg/400px-Edward_Said_and_Daniel_Barenboim_in_Sevilla%2C_2002_%28Said%29.jpg",
  "wikipedia_url": "https://en.wikipedia.org/wiki/Edward_Said",
  "open_library_url": "https://openlibrary.org/authors/OL26322A",
  "birth_year": 1935,
  "death_year": 2003
}
