{
  "name": "José Ortega y Gasset",
  "slug": "jos-ortega-y-gasset",
  "book_count": 2,
  "bio": "José Ortega y Gasset was a Spanish philosopher and essayist. He worked during the first half of the 20th century while Spain oscillated between monarchy, republicanism and dictatorship. His philosophy has been characterized as a \"philosophy of life\" that \"comprised a long-hidden beginning in a pragmatist metaphysics inspired by William James and with a general method from a realist phenomenology imitating Edmund Husserl, which served both his proto-existentialism and his realist historicism, which has been compared to both Wilhelm Dilthey and Benedetto Croce.\"",
  "photo_url": "https://upload.wikimedia.org/wikipedia/commons/thumb/5/5c/JoseOrtegayGasset.jpg/400px-JoseOrtegayGasset.jpg",
  "wikipedia_url": "https://en.wikipedia.org/wiki/Jos%C3%A9_Ortega_y_Gasset",
  "open_library_url": "https://openlibrary.org/authors/OL3941062A",
  "birth_year": 1883,
  "death_year": 1955,
  "_provenance": {
    "wikidata_qid": "wikidata_v1",
    "nationality": "wikidata_v1",
    "viaf_id": "wikidata_v1",
    "ol_author_key": "wikidata_v1",
    "movements": "wikidata_v1",
    "awards": "wikidata_v1"
  },
  "wikidata_qid": "Q153020",
  "nationality": [
    "ES"
  ],
  "viaf_id": "95155380",
  "ol_author_key": "/authors/OL3941062A",
  "movements": [
    "Noucentisme"
  ],
  "awards": [
    {
      "name": "Goethe Plaque of the City of Frankfurt",
      "year": 1949
    },
    {
      "name": "Goethe Medal for Art and Science",
      "year": 1932
    }
  ]
}
