{
  "name": "Margaret Laurence",
  "slug": "margaret-laurence",
  "book_count": 1,
  "bio": "Jean Margaret Laurence was a Canadian novelist and short story writer, and is one of the major figures in Canadian literature. She was also a founder of the Writers' Trust of Canada, a non-profit literary organization that seeks to encourage Canada's writing community.",
  "photo_url": "https://upload.wikimedia.org/wikipedia/en/d/de/MargaretLaurenceImage.jpg",
  "wikipedia_url": "https://en.wikipedia.org/wiki/Margaret_Laurence",
  "open_library_url": "https://openlibrary.org/authors/OL203016A",
  "birth_year": 1926,
  "death_year": 1987
}
