{
  "name": "Mario Vargas Llosa",
  "slug": "mario-vargas-llosa",
  "book_count": 3,
  "bio": "Jorge Mario Pedro Vargas Llosa, 1st Marquess of Vargas Llosa was a Peruvian novelist, journalist, essayist and politician. Vargas Llosa was one of the most significant Latin American novelists and essayists and one of the leading writers of his generation. Some critics consider him to have had a more substantial international impact and worldwide audience than any other writer of the Latin American Boom. In 2010, he won the Nobel Prize in Literature for \"his cartography of structures of power and his trenchant images of the individual's resistance, revolt, and defeat\".",
  "photo_url": "https://upload.wikimedia.org/wikipedia/commons/thumb/7/7a/Mario_Vargas_Llosa_LCCN2020733847_%28cropped%29.png/400px-Mario_Vargas_Llosa_LCCN2020733847_%28cropped%29.png",
  "wikipedia_url": "https://en.wikipedia.org/wiki/Mario_Vargas_Llosa",
  "open_library_url": "https://openlibrary.org/authors/OL74490A",
  "birth_year": 1936,
  "death_year": 2025
}
