{
  "name": "Paulo Freire",
  "slug": "paulo-freire",
  "book_count": 1,
  "bio": "Paulo Reglus Neves Freire was a Brazilian educator and Marxist philosopher whose work revolutionized global thought on education. He is best known for Pedagogy of the Oppressed, in which he reimagines teaching as a collaborative act of liberation rather than transmission. A founder of critical pedagogy, Freire’s influence spans literacy movements, liberation theology, postcolonial education, Marxism, and contemporary theories of social justice and learning. He is widely regarded as one of the most important educational theorists of the twentieth century, alongside figures such as John Dewey and Maria Montessori, and considered \"the Grandfather of Critical Theory\".",
  "photo_url": "https://upload.wikimedia.org/wikipedia/commons/thumb/b/be/Paulo_Freire_1977.jpg/400px-Paulo_Freire_1977.jpg",
  "wikipedia_url": "https://en.wikipedia.org/wiki/Paulo_Freire",
  "open_library_url": "https://openlibrary.org/authors/OL223954A",
  "birth_year": 1921,
  "death_year": 1997,
  "_provenance": {
    "wikidata_qid": "wikidata_v1",
    "nationality": "wikidata_v1",
    "viaf_id": "wikidata_v1",
    "ol_author_key": "wikidata_v1",
    "awards": "wikidata_v1"
  },
  "wikidata_qid": "Q164797",
  "nationality": [
    "BR"
  ],
  "viaf_id": "90070192",
  "ol_author_key": "/authors/OL223954A",
  "awards": [
    {
      "name": "honorary doctor of the University of Madrid Complutense",
      "year": 1991
    },
    {
      "name": "Order of Cultural Merit (Brazil)",
      "year": 2011
    },
    {
      "name": "honorary doctor of the University of Brasília"
    },
    {
      "name": "UNESCO Prize for Peace Education",
      "year": 1986
    },
    {
      "name": "honorary doctorate",
      "year": 1973
    }
  ]
}
