{
  "name": "Percy Bysshe Shelley",
  "slug": "percy-bysshe-shelley",
  "book_count": 3,
  "bio": "Percy Bysshe Shelley was an English writer who is considered one of the major English Romantic poets. A radical in his poetry as well as in his political and social views, Shelley did not achieve fame during his lifetime, but recognition of his achievements in poetry grew steadily following his death, and he became an important influence on subsequent generations of poets, including Robert Browning, Algernon Charles Swinburne, Thomas Hardy, and W. B. Yeats. American literary critic Harold Bloom describes him as \"a superb craftsman, a lyric poet without rival, and surely one of the most advanced sceptical intellects ever to write a poem.\"",
  "photo_url": "/tsundoku/cached/authors/percy-bysshe-shelley.jpg",
  "wikipedia_url": "https://en.wikipedia.org/wiki/Percy_Bysshe_Shelley",
  "open_library_url": "https://openlibrary.org/authors/OL20743A",
  "birth_year": 1792,
  "death_year": 1822,
  "_provenance": {
    "wikidata_qid": "wikidata_v1",
    "nationality": "wikidata_v1",
    "viaf_id": "wikidata_v1",
    "ol_author_key": "wikidata_v1",
    "movements": "wikidata_v1"
  },
  "wikidata_qid": "Q93343",
  "nationality": [
    "CH"
  ],
  "viaf_id": "95159449",
  "ol_author_key": "/authors/OL20743A",
  "movements": [
    "Romanticism"
  ],
  "photo_url_source": "https://upload.wikimedia.org/wikipedia/commons/thumb/5/57/Percy_Bysshe_Shelley_by_Alfred_Clint.jpg/400px-Percy_Bysshe_Shelley_by_Alfred_Clint.jpg",
  "photo_cached_at": "2026-05-03T03:13:07+00:00"
}
