{
  "name": "Romain Rolland",
  "slug": "romain-rolland",
  "book_count": 1,
  "bio": "Romain Rolland was a French dramatist, novelist, essayist, art historian and mystic who was awarded the Nobel Prize for Literature in 1915 \"as a tribute to the lofty idealism of his literary production and to the sympathy and love of truth with which he has described different types of human beings\".",
  "photo_url": "https://upload.wikimedia.org/wikipedia/commons/thumb/2/29/Romain_Rolland_de_face_au_balcon%2C_Meurisse%2C_1914_retouche.jpg/400px-Romain_Rolland_de_face_au_balcon%2C_Meurisse%2C_1914_retouche.jpg",
  "wikipedia_url": "https://en.wikipedia.org/wiki/Romain_Rolland"
}