{
  "title": "Algebra",
  "author": "Michael Artin",
  "category": "Mathematics",
  "priority": 1,
  "slug": "algebra",
  "tags": [
    "math"
  ],
  "cover_url": "https://covers.openlibrary.org/b/id/8616136-M.jpg",
  "cover_url_large": "https://covers.openlibrary.org/b/id/8616136-L.jpg",
  "open_library_url": "https://openlibrary.org/works/OL19825343W",
  "first_published": 2009,
  "language": "eng",
  "description": "\"Algebra, Second Edition, by Michael Artin, is ideal for the honors undergraduate or introductory graduate course. The second edition of this classic text incorporates twenty years of feedback and the author's own teaching experience. The text discusses concrete topics of algebra in greater detail than most texts, preparing students for the more abstract concepts; linear algebra is tightly integrated throughout.\" -- Publisher's description.",
  "isbn": "0132413779",
  "google_books_url": "http://books.google.com/books?id=TUF6zwEACAAJ&dq=Algebra+Michael+Artin&hl=&source=gbs_api",
  "reading_status": "want",
  "oclc_id": "818846310",
  "worldcat_url": "https://www.worldcat.org/oclc/818846310",
  "lccn": "2010017573",
  "subjects": [
    "Algebra",
    "Mathematics",
    "Isomorphisms (Mathematics)",
    "Symmetry",
    "Group theory",
    "Bilinear forms",
    "Rings",
    "Factorization (Mathematics)",
    "Modules (Algebra)",
    "Galois theory"
  ],
  "copyright_status": "in_copyright"
}