{
  "title": "Botchan",
  "author": "Natsume Sōseki",
  "category": "Literature",
  "priority": 1,
  "slug": "botchan",
  "tags": [
    "adventure",
    "humor"
  ],
  "cover_url": "https://covers.openlibrary.org/b/id/4788315-M.jpg",
  "cover_url_large": "https://covers.openlibrary.org/b/id/4788315-L.jpg",
  "open_library_url": "https://openlibrary.org/works/OL1174969W",
  "first_published": 1918,
  "language": "eng",
  "description": "Publisher description: The setting is Japan's deep south, where the author himself spent some time teaching English in a boys' school. Into this conservative world, with its social proprieties and established pecking order, breezes Botchan, down from the big city, with scant respect for either his elders or his noisy young charges; and the result is a chain of collisions large and small.",
  "isbn": "4770030487",
  "pages": 188,
  "google_books_url": "http://books.google.com/books?id=DK9UinuPcYcC&dq=Botchan+Natsume+S%C5%8Dseki&hl=&source=gbs_api",
  "reading_status": "want",
  "oclc_id": "57576134",
  "worldcat_url": "https://www.worldcat.org/oclc/57576134",
  "lccn": "43035779",
  "librivox_url": "https://librivox.org/botchan-by-soseki-natsume/",
  "subjects": [
    "Fiction",
    "Fiction, humorous",
    "Japan, fiction",
    "Near and far eastern fiction (fictional works by one author)",
    "Teachers, fiction",
    "Fiction, humorous, general",
    "Boys",
    "Fiction, action & adventure",
    "FICTION / General",
    "Fiction, general"
  ],
  "copyright_status": "public_domain"
}