{
  "title": "Darwinia",
  "author": "Robert Charles Wilson",
  "category": "Science Fiction",
  "priority": 2,
  "slug": "darwinia",
  "tags": [
    "sci-fi",
    "utopian"
  ],
  "cover_url": "https://covers.openlibrary.org/b/id/8128329-M.jpg",
  "cover_url_large": "https://covers.openlibrary.org/b/id/8128329-L.jpg",
  "open_library_url": "https://openlibrary.org/works/OL8339326W",
  "first_published": 1998,
  "language": "eng",
  "description": "A novel of a very different 20th Century",
  "isbn": "0765319055",
  "pages": 332,
  "google_books_url": "http://books.google.com/books?id=O0CXPGJ8N_gC&dq=Darwinia+Robert+Charles+Wilson&hl=&source=gbs_api",
  "reading_status": "read",
  "oclc_id": "153578197",
  "worldcat_url": "https://www.worldcat.org/oclc/153578197",
  "lccn": "98014538",
  "copyright_status": "in_copyright",
  "ddc": [
    "813.54"
  ],
  "lcc": [
    "PR-9199.30000000.W4987D37",
    "PR-9199.30000000.W4987 D37 1998",
    "PS-8595.00000000.I587 D37 1998"
  ],
  "subject_facet": [
    "Fiction",
    "Fiction, alternative history",
    "Fiction, science fiction, general",
    "Imaginary histories",
    "Science fiction",
    "Utopias"
  ],
  "ol_work_key": "/works/OL8339326W",
  "_provenance": {
    "editions_count": "ol_firstedition_v1",
    "first_published": "wikidata_v1",
    "first_published_circa": "wikidata_v1",
    "representative_edition_key": "ol_firstedition_v1",
    "wikidata_qid": "wikidata_v1",
    "original_title": "wikidata_v1",
    "original_language": "wikidata_v1"
  },
  "editions_count": 7,
  "first_published_circa": false,
  "representative_edition_key": "/books/OL8053734M",
  "wikidata_qid": "Q3016630",
  "original_title": "Darwinia",
  "original_language": "eng"
}
