{
  "title": "Embassytown",
  "author": "China Miéville",
  "category": "Contemporary Speculative Fiction",
  "priority": 1,
  "slug": "embassytown",
  "tags": [
    "sci-fi"
  ],
  "cover_url": "https://covers.openlibrary.org/b/id/7276258-M.jpg",
  "cover_url_large": "https://covers.openlibrary.org/b/id/7276258-L.jpg",
  "open_library_url": "https://openlibrary.org/works/OL16001889W",
  "first_published": 2011,
  "language": "eng",
  "description": "Embassytown: a city of contradictions on the outskirts of the universe. Avice is an immerser, a traveller on the immer, the sea of space and time below the everyday, now returned to her birth planet.",
  "isbn": "9780345524492",
  "pages": 369,
  "google_books_url": "http://books.google.com/books?id=OmE9DwAAQBAJ&dq=Embassytown+China+Mi%C3%A9ville&hl=&source=gbs_api",
  "reading_status": "want",
  "subjects": [
    "Fiction",
    "Space warfare",
    "Human-alien encounters",
    "Loyalty",
    "Life on other planets",
    "Science-Fiction-Literatur",
    "Science-Fiction",
    "Englisch",
    "Fiction, science fiction, general"
  ],
  "copyright_status": "in_copyright"
}