{
  "title": "Flowers for Algernon",
  "author": "Daniel Keyes",
  "category": "Literature",
  "priority": 1,
  "slug": "flowers-for-algernon",
  "tags": [
    "npr-top-100-sff"
  ],
  "reading_status": "read",
  "description": "",
  "cover_url": "",
  "cover_url_large": "",
  "open_library_url": "",
  "google_books_url": "",
  "isbn": "9780891908753",
  "pages": 0,
  "first_published": 1966,
  "language": "eng",
  "subjects": [
    "NPR Top 100 Science Fiction and Fantasy"
  ],
  "ddc": [
    "[Fic]",
    "813",
    "813.54"
  ],
  "lcc": [
    "PS-3561.00000000.E769 F5 1987",
    "PS-3561.00000000.E769F56 2017",
    "PS-3561.00000000 E88 F64 1966",
    "PZ-0007.00000000.K522Fl 1988",
    "PS-3561.00000000.E769 F68 1994",
    "PS-3561.00000000.E769F56 2002",
    "PS-3561.00000000.E769",
    "PZ-0073.00000000.K4725 1997x",
    "PS-3561.00000000.E769F56 1990z",
    "PS-3516.00000000.E769 F56 1972",
    "PS-3561.00000000.E769 Fl",
    "PS-3561.00000000.E769 F56 1995",
    "PZ-0007.00000000.K522 Fl 1988",
    "PS-3561.00000000.E769 F56 1966",
    "PZ-0004.00000000.K4453 Fl",
    "PS-3561.00000000.E769 F5617 2006",
    "PS-3561.00000000.E769 F56 2002",
    "PS-3561.00000000.E769 F56 2004",
    "PS-3561.00000000.E769 F56 1990z",
    "PS-3561.00000000.E769 F5616 1989",
    "PS-3561.00000000.E769 F5616 1999",
    "PS-3521.00000000 E85, Fℓ2",
    "PS-3561.00000000.E769F56 2004"
  ],
  "subject_facet": [
    "American Science fiction",
    "Brain",
    "Cerebro",
    "Cerveau",
    "Children's fiction",
    "Chirurgie",
    "Cirugía",
    "Ficción juvenil",
    "Fiction",
    "Fiction, science fiction, general",
    "Gifted persons",
    "Grifted peoples",
    "Juvenile fiction",
    "Large type books",
    "Mentally handicapped",
    "Nebula Award",
    "Niños superdotados",
    "Novela",
    "Open Library Staff Picks",
    "People with mental disabilities",
    "People with mental disabilities, fiction",
    "Personas dotadas",
    "Personnes ayant une déficience intellectuelle",
    "Psychological fiction",
    "Readers",
    "Reading Level-Grade 10",
    "Reading Level-Grade 11",
    "Reading Level-Grade 12",
    "Reading Level-Grade 7",
    "Reading Level-Grade 8",
    "Reading Level-Grade 9",
    "Retrasados mentales",
    "Romans, nouvelles",
    "Science fiction",
    "Surdoués",
    "Surgery",
    "Young adult fiction",
    "award:nebula_award=novel",
    "dementia",
    "institutionalization",
    "phenylketonuria"
  ],
  "ol_work_key": "/works/OL515754W",
  "_provenance": {
    "editions_count": "ol_firstedition_v1",
    "first_published": "ol_firstedition_v1",
    "first_published_circa": "ol_firstedition_v1",
    "first_edition_isbn": "ol_firstedition_v1",
    "representative_edition_key": "ol_firstedition_v1"
  },
  "editions_count": 79,
  "first_published_circa": false,
  "representative_edition_key": "/books/OL11295964M",
  "copyright_status": "in_copyright"
}