{
  "title": "Letters to a Young Poet",
  "author": "Rainer Maria Rilke",
  "category": "Literature",
  "priority": 1,
  "slug": "letters-to-a-young-poet",
  "tags": [
    "biography"
  ],
  "cover_url": "https://covers.openlibrary.org/b/id/6874224-M.jpg",
  "cover_url_large": "https://covers.openlibrary.org/b/id/6874224-L.jpg",
  "open_library_url": "https://openlibrary.org/works/OL3800761W",
  "first_published": 1656,
  "language": "eng",
  "description": "This modern translation of Rilke's classic letters of wisdom and advice touches upon a wide range of subjects that are sure to be of interest to writers, artists, and thinkers.",
  "isbn": "9781577311553",
  "pages": 129,
  "google_books_url": "http://books.google.com/books?id=CjEuAgAAQBAJ&dq=Letters+to+a+Young+Poet+Rainer+Maria+Rilke&hl=&source=gbs_api",
  "reading_status": "read",
  "copyright_status": "public_domain",
  "ddc": [
    "836.912",
    "831.912 B",
    "831.912"
  ],
  "lcc": [
    "PT-2635.00000000.I65 Z48 2021",
    "PT-2635.00000000.I65Z488 2000",
    "PT-2635.00000000.I65 Z537 1967",
    "PT-2635.00000000.I65 Z53713 1993",
    "PT-2635.00000000.I65 Z537",
    "PT-2635.00000000.I65",
    "PT-2635.00000000.I65 Z488 2011",
    "PT-2635.00000000.I65 Z53713 1954",
    "PT-2635.00000000.I65Z48 2021",
    "PT-2635.00000000.I64 Z53713 1945",
    "PT-2635.00000000.I65 Z53718 1990",
    "PT-2635.00000000.I65 Z48813 2011",
    "PT-2635.00000000.I65Z53713",
    "PT-2635.00000000.I65 Z488 1984",
    "PT-2635.00000000.I65 Z53713 2001",
    "PT-2635.00000000.I65 Z488 1992",
    "PT-2635.00000000.I65 Z64 [1984]",
    "PT-2635.00000000.I64 Z53713 2021",
    "PT-2635.00000000.I65 A6 2013",
    "PT-2635.00000000.I65Z52513",
    "PT-2635.00000000.I65 Z53713 2000",
    "PT-2635.00000000.I65 Z52513 2002",
    "PT-2635.00000000.I65 Z537 1947",
    "PT-2635.00000000.I65Z488 2011",
    "PT-2635.00000000.I65 Z54 1958",
    "PT-2635.00000000.I65 Z488 1987",
    "PT-2635.00000000.I65 Z54 1962",
    "PT-2635.00000000.I65 Z53713 1934",
    "PT-2635.00000000.I65 Z542 1941b"
  ],
  "subject_facet": [
    "20th century",
    "Accessible book",
    "Austrian Authors",
    "Austrian literature",
    "Authors",
    "Authors, correspondence",
    "Authors, german",
    "Autores alemanes",
    "Biography",
    "Correspondance",
    "Correspondence",
    "Correspondence (Rilke, Rainer Maria)",
    "Correspondencia",
    "Creation (Literary, artistic, etc.)",
    "Criticism and interpretation",
    "Création littéraire",
    "Ecrivains allemands",
    "German Authors",
    "Germanic literature",
    "Kappus, franz xaver, 1883-1966",
    "LITERARY COLLECTIONS / Letters",
    "Letters",
    "Literature, collections",
    "Love",
    "POETRY / General",
    "Poetry (poetic works by one author)",
    "Poetry, history and criticism",
    "Poets, correspondence",
    "Protected DAISY",
    "Rilke, rainer maria, 1875-1926",
    "Sadness",
    "Solitude",
    "Traducciones al español",
    "Translations into English",
    "Translations into Spanish",
    "Écrivains allemands",
    "Écrivains autrichiens"
  ],
  "ol_work_key": "/works/OL3800761W",
  "_provenance": {
    "editions_count": "ol_firstedition_v1",
    "first_published": "ol_firstedition_v1",
    "first_published_circa": "ol_firstedition_v1",
    "first_edition_isbn": "ol_firstedition_v1",
    "representative_edition_key": "ol_firstedition_v1"
  },
  "editions_count": 144,
  "first_published_circa": false,
  "first_edition_isbn": null,
  "representative_edition_key": "/books/OL60943923M"
}
