{
  "title": "Metaphysics",
  "author": "Aristotle",
  "category": "Philosophy",
  "priority": 2,
  "slug": "metaphysics",
  "tags": [
    "astronomy",
    "physics"
  ],
  "cover_url": "https://covers.openlibrary.org/b/id/10702956-M.jpg",
  "cover_url_large": "https://covers.openlibrary.org/b/id/10702956-L.jpg",
  "open_library_url": "https://openlibrary.org/works/OL20966539W",
  "first_published": 1968,
  "language": "eng",
  "description": "This new translation of Aristotle's Metaphysics in its entirety is a model of accuracy and consistency, presented with a wealth of annotation and commentary. Sequentially numbered endnotes provide the information most needed at each juncture, while a detailed Index of Terms guides the reader to places where focused discussion of key notions occurs. An illuminating general Introduction describes the book that lies ahead, explaining what it is about, what it is trying to do, how it goes about doin...",
  "isbn": "9781624664410",
  "pages": 708,
  "google_books_url": "https://play.google.com/store/books/details?id=prGgCwAAQBAJ&source=gbs_api",
  "reading_status": "read",
  "subjects": [
    "Metaphysics",
    "Early works to 1800",
    "Metaphysica (Aristoteles)",
    "Rhetoric, ancient",
    "Ethics, greece",
    "Athens (greece), politics and government",
    "Meteorology, early works to 1800",
    "Aristotle",
    "Philosophers, greece",
    "Astronomy, early works to 1800"
  ],
  "librivox_url": "https://librivox.org/metaphysics-by-aristotle/",
  "copyright_status": "public_domain",
  "lcc": [
    "B--0434.00000000.A5M5 2018"
  ],
  "subject_facet": [
    "Economics",
    "Ethics",
    "Metaphysics",
    "Philosophy"
  ],
  "ol_work_key": "/works/OL20966539W"
}
