{
  "title": "Player of Games",
  "author": "Iain M. Banks",
  "category": "Fantasy",
  "priority": 1,
  "slug": "player-of-games",
  "tags": [
    "fantasy",
    "sci-fi"
  ],
  "cover_url": "https://covers.openlibrary.org/b/id/44077-M.jpg",
  "cover_url_large": "https://covers.openlibrary.org/b/id/44077-L.jpg",
  "open_library_url": "https://openlibrary.org/works/OL100779W",
  "first_published": 1988,
  "language": "eng",
  "description": "The Culture — a human/machine symbiotic society — has thrown up many great Game Players, and one of the greatest is Gurgeh Jernau Morat Gurgeh. The Player of Games. Master of every board, computer and strategy. Bored with success, Gurgeh travels to the Empire of Azad, cruel and incredibly wealthy, to try their fabulous game. . . a game so complex, so like life itself, that the winner becomes emperor. Mocked, blackmailed, almost murdered, Gurgeh accepts the game, and with it the challenge of his ...",
  "isbn": "9780316095860",
  "pages": 281,
  "google_books_url": "https://play.google.com/store/books/details?id=GsCT8lPbYFMC&source=gbs_api",
  "reading_status": "read",
  "subjects": [
    "OverDrive",
    "Fiction",
    "Science Fiction",
    "Science Fiction & Fantasy",
    "Accessible book",
    "Protected DAISY",
    "In library",
    "Long Now Manual for Civilization"
  ],
  "copyright_status": "in_copyright"
}
