{
  "title": "Rat Queens #1",
  "author": "Kurtis Wiebe",
  "category": "Literature",
  "priority": 2,
  "slug": "rat-queens-1",
  "tags": [
    "google-play-library"
  ],
  "reading_status": "read",
  "description": "Who are the Rat Queens? A pack of booze-guzzling, death-dealing battle maidens-for-hire, and they're in the business of killing all gods' creatures for profit. It's also a darkly comedic fantasy series starring Hannah the Rockabilly Elven Mage, Violet the Hipster Dwarven Fighter, Dee the Atheist Human Cleric and Betty the Hippy Hobbit Thief. This modern spin on an old school genre is a violent monster-killing epic that is like Buffy meets Tank Girl in a Lord of the Rings world on crack!",
  "cover_url": "https://books.google.com/books/content?id=u3cZAgAAQBAJ&printsec=frontcover&img=1&zoom=1&edge=curl&source=gbs_api",
  "first_published": 2013,
  "pages": 32,
  "google_books_url": "https://play.google.com/store/books/details?id=u3cZAgAAQBAJ&source=gbs_api",
  "language": "eng",
  "copyright_status": "in_copyright"
}