{
  "title": "Samarkand",
  "author": "Amin Maalouf",
  "category": "Non-Western Literature",
  "priority": 2,
  "slug": "samarkand",
  "tags": [],
  "description": "A gripping historical novel set in 11th century Persia that imagines the life of poet and philosopher Omar Khayyam Accused of mocking the inviolate codes of Islam, the Persian poet and sage Omar Khayyam fortuitously finds sympathy with the very man who is to judge his alleged crimes. Recognising genius, the judge decides to spare him and gives him instead a small, blank book, encouraging him to confine his thoughts to it alone. Thus begins the seamless blend of fact and fiction that is Samarkand...",
  "cover_url": "https://books.google.com/books/content?id=r3o0AgAAQBAJ&printsec=frontcover&img=1&zoom=1&edge=curl&source=gbs_api",
  "cover_url_large": "https://books.google.com/books/content?id=r3o0AgAAQBAJ&printsec=frontcover&img=1&zoom=1&edge=curl&source=gbs_api",
  "isbn": "9780748131242",
  "first_published": 2012,
  "pages": 291,
  "subjects": [
    "Fiction"
  ],
  "language": "eng",
  "google_books_url": "https://play.google.com/store/books/details?id=r3o0AgAAQBAJ&source=gbs_api",
  "reading_status": "want"
}