{
  "title": "The Price of Inequality",
  "author": "Joseph Stiglitz",
  "category": "Economics",
  "priority": 1,
  "slug": "the-price-of-inequality",
  "tags": [],
  "cover_url": "https://covers.openlibrary.org/b/id/9328023-M.jpg",
  "cover_url_large": "https://covers.openlibrary.org/b/id/9328023-L.jpg",
  "open_library_url": "https://openlibrary.org/works/OL20662505W",
  "first_published": 2013,
  "description": "About the problem of social inequality in the United States.",
  "isbn": "9780393088694",
  "pages": 448,
  "google_books_url": "http://books.google.com/books?id=IPGeZnDMppUC&dq=The+Price+of+Inequality+Joseph+Stiglitz&hl=&source=gbs_api",
  "language": "eng",
  "reading_status": "read",
  "copyright_status": "in_copyright",
  "subjects": [
    "Business & Economics"
  ],
  "ddc": [
    "305.50973"
  ],
  "lcc": [
    "HC-0110.00000000.I5 S867 2012",
    "HC-0110.00000000.I5S867 2012"
  ],
  "subject_facet": [
    "305.50973",
    "Economic conditions",
    "Equality",
    "Equality--united states",
    "Hc110.i5 s867 2012",
    "Income distribution",
    "Income distribution, united states",
    "Income distribution--social aspects",
    "Income distribution--social aspects--united states",
    "New York Times bestseller",
    "New York Times reviewed",
    "Social classes, united states",
    "Social conditions",
    "United states, economic conditions, 21st century",
    "United states, social conditions, 21st century",
    "nyt:hardcover-nonfiction=2012-07-01"
  ],
  "ol_work_key": "/works/OL16618086W"
}
