{
  "title": "The Theater and Its Double",
  "author": "Antonin Artaud",
  "category": "Drama",
  "priority": 2,
  "slug": "the-theater-and-its-double",
  "tags": [],
  "cover_url": "https://covers.openlibrary.org/b/id/569546-M.jpg",
  "cover_url_large": "https://covers.openlibrary.org/b/id/569546-L.jpg",
  "open_library_url": "https://openlibrary.org/works/OL794769W",
  "first_published": 1958,
  "language": "eng",
  "description": "A collection of manifestos originally published in 1938, in which the French artist and philosopher attacks conventional assumptions about the drama, and calls for the influx of irrational material - based on dreams, religion, and emotion - in order to make the theater vital for modern audiences.",
  "isbn": "0802150306",
  "pages": 174,
  "google_books_url": "http://books.google.com/books?id=bmf8CMzu3kIC&dq=The+Theater+and+Its+Double+Antonin+Artaud&hl=&source=gbs_api",
  "reading_status": "read",
  "copyright_status": "likely_public_domain",
  "subjects": [
    "Theater",
    "Teatro (Producao E Direcao)",
    "Theatre",
    "Aufsatzsammlung"
  ]
}