{
  "title": "The War of the Worlds",
  "author": "H.G. Wells",
  "category": "Fantasy",
  "priority": 1,
  "slug": "the-war-of-the-worlds",
  "tags": [
    "children",
    "fantasy",
    "sci-fi",
    "war",
    "le-monde-100",
    "npr-top-100-sff"
  ],
  "cover_url": "https://covers.openlibrary.org/b/id/36314-M.jpg",
  "cover_url_large": "https://covers.openlibrary.org/b/id/36314-L.jpg",
  "open_library_url": "https://openlibrary.org/works/OL52114W",
  "language": "eng",
  "description": "The seminal masterpiece of alien invasion, The War of the Worlds (1898) conjures a terrifying, tentacled race of Martians who devastate the Earth and feed on their human victims while their voracious vegetation, the red weed, spreads over the ruined planet. After the novel's hero finds himself trapped in what is left of London, despairing at the destruction of human civilization, he discovers that life on Earth is more resilient than he had imagined. Adapted by Orson Welles for his notorious 193...",
  "isbn": "9798719609539",
  "pages": 294,
  "google_books_url": "http://books.google.com/books?id=0A9azgEACAAJ&dq=The+War+of+the+Worlds+H.G.+Wells&hl=&source=gbs_api",
  "reading_status": "read",
  "copyright_status": "public_domain",
  "subjects": [
    "Category: British Literature",
    "Category: Classics of Literature",
    "Category: Novels",
    "Category: Science-Fiction & Fantasy",
    "Classic Literature",
    "Diseases",
    "Fiction",
    "Imaginary wars and battles",
    "Imaginary wars and battles -- Fiction",
    "Invasions",
    "Juvenile fiction",
    "Life on other planets -- Fiction",
    "Mars (Planet) -- Fiction",
    "Martians",
    "Martians -- Fiction",
    "Movie Books",
    "Open Library Staff Picks",
    "Science Fiction",
    "Science Fiction & Fantasy",
    "Science fiction",
    "Space warfare",
    "Space warfare -- Fiction",
    "War stories"
  ],
  "librivox_url": "https://librivox.org/the-war-of-the-worlds-by-h-g-wells-group/",
  "gutenberg_id": 36,
  "gutenberg_url": "https://www.gutenberg.org/ebooks/36",
  "gutenberg_read_url": "https://www.gutenberg.org/ebooks/36.html.images",
  "ddc": [
    "823.912",
    "823",
    "[Fic]"
  ],
  "lcc": [
    "PR-5774.00000000.W3 2019",
    "PR-5774.00000000.W3 2001",
    "PZ-0007.00000000.S24864 War 2007",
    "PR-5774.00000000.W3 2015",
    "PR-5774.00000000.W3 2001b",
    "PR-5774.00000000.W3 1997",
    "PZ-0003.00000000.W465 Wa22",
    "PZ-0007.00000000.W4643 War 2001",
    "PZ-0007.00000000.W4647 War 1999",
    "PR-5774.00000000.W3 1993b",
    "PZ-0007.70000000.M53War 2014",
    "PR-5774.00000000 W",
    "PR-5774.00000000.W3 F7 1906",
    "PR-5774.00000000.W3 2012",
    "PR-5774.00000000.W37 1983",
    "PR-5774.00000000.W3 2002",
    "PR-5774.00000000.W3 1992",
    "PZ-0007.00000000.W4643 War 2007",
    "PZ-0003.00000000.W465 Wa19",
    "PR-5774.00000000.W3 2009",
    "PR-5774.00000000.W3 2005d",
    "PZ-0003.00000000.W465 Wa8",
    "PR-5774.00000000.W3 2005dx",
    "PR-5774.00000000 Wa19",
    "PR-5774.00000000.W3 2014",
    "PR-5774.00000000 Wa8",
    "PZ-0007.00000000.W4643 War 2007b",
    "PR-5774.00000000",
    "PR-5774.00000000.W3 1995b",
    "PZ-0007.00000000.W4643War 2014",
    "PZ-0007.70000000.M53 Hgw 2014",
    "PR-5774.00000000.W3 2017",
    "PR-5774.00000000.W3 P6 1981",
    "PR-5774.00000000.W3 2006",
    "PR-5774.00000000 W3 S7",
    "PZ-0007.00000000.W4643War 2001",
    "PR-5774.00000000.W3 1993",
    "PR-5774.00000000.W3 2005c",
    "PR-5774.00000000.W3 2007",
    "PZ-0003.00000000.W465 Ti15",
    "PR-5774.00000000.W3 1898",
    "PR-5774.00000000.W3718 2005",
    "PR-5774.00000000.W3 2003",
    "PR-5774.00000000 Wa22",
    "PZ-0003.00000000.W465 Wa25",
    "PR-5774.00000000.W3 1995",
    "PR-5774.00000000.W37 1986",
    "PR-5774.00000000 Ti15",
    "PR-5772.00000000 2012b",
    "PR-5770.00000000",
    "PR-5774.00000000.W3 M66 2009",
    "PE-1128.00000000.M3 2008",
    "PZ-0007.70000000.F65 War 2011",
    "PR-5774.00000000.W3 2005b",
    "PR-5774.00000000.W3 1964",
    "PZ-0003.00000000.W465 W",
    "PR-5774.00000000.W3 2005",
    "PZ-0007.00000000.S24864War 2007",
    "PR-5774.00000000 W3 1898",
    "PZ-0007.00000000.W4647War 1999",
    "PZ-0007.00000000.W4643 War 2014",
    "PR-5774.00000000 Wa25",
    "PR-5774.00000000.W3 2006b"
  ],
  "subject_facet": [
    "823.912",
    "Adaptations",
    "Adventure and adventurers, fiction",
    "Aladdin (legendary character), fiction",
    "British and irish fiction (fictional works by one author)",
    "Children's fiction",
    "Classic Literature",
    "Comic books, strips",
    "Diseases",
    "Earth",
    "English Science fiction",
    "English language",
    "English literature",
    "Examinations",
    "Extraterrestrial beings",
    "Extraterrestrial beings, fiction",
    "Ficcion",
    "Fiction",
    "Fiction, action & adventure",
    "Fiction, fantasy, general",
    "Fiction, science fiction, action & adventure",
    "Fiction, science fiction, general",
    "Fiction, war & military",
    "Graphic novels",
    "Guerra",
    "Guerra espacial",
    "Guerras imaginarias",
    "Human-alien encounters",
    "Imaginary wars and battles",
    "Imaginary wars and battles -- Fiction",
    "Imaginary wars and battles in literature",
    "Imaginary wars and battles--fiction",
    "Invasions",
    "Juvenile fiction",
    "Life on other planets",
    "Life on other planets, fiction",
    "Literature",
    "Long Now Manual for Civilization",
    "Mars (Planet)",
    "Mars (Planet) -- Fiction",
    "Martians",
    "Novela",
    "Open Library Staff Picks",
    "Outer space, fiction",
    "Pr5774 .w3 2005dx",
    "Romance Ingles",
    "SAT (Educational test)",
    "Science Fiction & Fantasy",
    "Science fiction",
    "Seres extraterrestres",
    "Space vehicles",
    "Space warfare",
    "Space warfare -- Fiction",
    "Space warfare--fiction",
    "Study guides",
    "Vocabulary",
    "War stories",
    "War, fiction",
    "Wells, h. g. (herbert george), 1866-1946",
    "open_syllabus_project"
  ],
  "ol_work_key": "/works/OL52114W",
  "_provenance": {
    "editions_count": "ol_firstedition_v1",
    "representative_edition_key": "ol_firstedition_v1"
  },
  "editions_count": 400,
  "representative_edition_key": "/books/OL59048283M"
}
