{
  "title": "The Extraordinary Adventures of Arsène Lupin, Gentleman-Burglar",
  "author": "Maurice Leblanc",
  "category": "Literature",
  "priority": 2,
  "slug": "the-extraordinary-adventures-of-ars-ne-lupin-gentleman-burglar",
  "tags": [
    "google-play-library"
  ],
  "reading_status": "read",
  "description": "Arsène Lupin, with his characteristic wit, plots over the course of nine short stories to steal many of France’s best antiques and artworks from under their owners’ noses. Only his classic opponent Detective Ganimard has the brilliance to attempt to foil Arsène’s plans, albeit with mixed results. This first collection of nine Arsène Lupin stories were originally serialised in the magazine Je Sais Tout from 1905 and translated into English in 1910. The final story of the set features Herlock Shol",
  "cover_url": "https://books.google.com/books/content?id=1x0ZEAAAQBAJ&printsec=frontcover&img=1&zoom=1&edge=curl&source=gbs_api",
  "first_published": 2018,
  "pages": 530,
  "google_books_url": "https://play.google.com/store/books/details?id=1x0ZEAAAQBAJ&source=gbs_api",
  "language": "eng",
  "copyright_status": "in_copyright",
  "subjects": [
    "French Detective and mystery stories",
    "Parodies, imitations",
    "Romance Frances",
    "Fiction",
    "Arséne Lupin (Fictitious character)",
    "Adventure stories, French",
    "Translations into English",
    "Burglars",
    "Adventures",
    "Arsène Lupin (Fictitious character)"
  ]
}