{
  "title": "The Secret City",
  "author": "Chuck Kelly",
  "category": "Literature",
  "priority": 2,
  "slug": "the-secret-city",
  "tags": [
    "google-play-library"
  ],
  "reading_status": "read",
  "description": "On his first day at the Learning Center on the enchanted planet Otherland (which is not far from planet Earth) thirteen-year-old Bunker Charles' personal flying zoomer is borrowed by a student named CJ, who takes off and flies to the mountains. Bunker and his friend, Gittel, follow him. After a few misadventures along the way they come across the mysterious Secret City that is hidden among snow-capped mountains. Bunker and Gittel meet Victor, a tall silver man who shows them around the Secret Ci",
  "cover_url": "https://books.google.com/books/content?id=E34BrgEACAAJ&printsec=frontcover&img=1&zoom=1&source=gbs_api",
  "isbn": "0692364889",
  "first_published": 2015,
  "pages": 364,
  "google_books_url": "http://books.google.com/books?id=E34BrgEACAAJ&dq=intitle:The+Secret+City&hl=&source=gbs_api",
  "language": "eng",
  "copyright_status": "in_copyright",
  "ol_work_key": "/works/OL20318004W"
}
