{
  "title": "The Talleyrand Maxim",
  "author": "J. S. Fletcher",
  "category": "Literature",
  "priority": 2,
  "slug": "the-talleyrand-maxim",
  "tags": [
    "google-play-library",
    "mystery",
    "thriller"
  ],
  "reading_status": "read",
  "description": "Linford Pratt had once during one of his visits to the town Reference Library, lighted on a maxim of that other unscrupulous person, Prince Talleyrand: \"With time and patience the mulberry leaf is turned into satin.\" This seemed to Linford Pratt one of the finest and soundest pieces of wisdom which he had ever known put into words.",
  "cover_url": "https://books.google.com/books/content?id=C7FMPQAACAAJ&printsec=frontcover&img=1&zoom=1&source=gbs_api",
  "isbn": "0809566230",
  "first_published": 2004,
  "pages": 236,
  "google_books_url": "http://books.google.com/books?id=C7FMPQAACAAJ&dq=intitle:The+Talleyrand+Maxim&hl=&source=gbs_api",
  "language": "eng",
  "copyright_status": "public_domain",
  "librivox_url": "https://librivox.org/the-talleyrand-maxim-by-j-s-fletcher/",
  "gutenberg_id": 9834,
  "gutenberg_url": "https://www.gutenberg.org/ebooks/9834",
  "gutenberg_read_url": "https://www.gutenberg.org/ebooks/9834.html.images",
  "ddc": [
    "[Fic]"
  ],
  "lcc": [
    "PR-6011.00000000.L5 Ta2",
    "PZ-0003.00000000.F634 Ta2"
  ],
  "subject_facet": [
    "Detective and mystery stories",
    "Fiction",
    "Fiction, mystery & detective, general",
    "Fiction, thrillers, suspense",
    "Mystery",
    "Wills in fiction"
  ],
  "ol_work_key": "/works/OL1797757W",
  "_provenance": {
    "editions_count": "ol_firstedition_v1",
    "first_published": "ol_firstedition_v1",
    "first_published_circa": "ol_firstedition_v1",
    "representative_edition_key": "ol_firstedition_v1"
  },
  "editions_count": 115,
  "first_published_circa": false,
  "representative_edition_key": "/books/OL9606713M"
}
