{
  "title": "The Ascent of Money",
  "author": "Niall Ferguson",
  "category": "Economics",
  "priority": 1,
  "slug": "the-ascent-of-money",
  "tags": [],
  "cover_url": "https://covers.openlibrary.org/b/id/6327852-M.jpg",
  "cover_url_large": "https://covers.openlibrary.org/b/id/6327852-L.jpg",
  "open_library_url": "https://openlibrary.org/works/OL792952W",
  "first_published": 2008,
  "language": "eng",
  "description": "Ferguson tells the human story behind the evolution of money, from its origins in ancient Mesopotamia to the latest Wall Street upheavals. The author shows that finance is, in fact, the foundation of human progress.",
  "isbn": "1594201927",
  "pages": 452,
  "google_books_url": "http://books.google.com/books?id=JA_IYJ0P4ZkC&dq=The+Ascent+of+Money+Niall+Ferguson&hl=&source=gbs_api",
  "reading_status": "want",
  "copyright_status": "in_copyright",
  "subjects": [
    "Economic history",
    "Economics",
    "Finance",
    "History",
    "International finance",
    "Money",
    "Nonfiction",
    "Origin",
    "nyt:hardcover-nonfiction=2008-12-14",
    "New York Times bestseller"
  ]
}