{
  "title": "Ticket No",
  "author": "Jules Verne",
  "category": "Literature",
  "priority": 2,
  "slug": "ticket-no",
  "tags": [
    "adventure",
    "google-play-library"
  ],
  "reading_status": "read",
  "description": "Here is one of those \"forgotten\" works. Ticket No. \"9672\" is a fascinating tale of two women who live in a Norway Inn. Dame Hansen is a foolish creature whose mistakes must be dealt with by her daughter Hulda. Coming to their aid is their brother Joel and the remarkable Sylvius Hogg, who helps them all after the young Hansens rescue him from the edge of the Rjukanfos Waterfall.",
  "cover_url": "https://books.google.com/books/content?id=92V7EAAAQBAJ&printsec=frontcover&img=1&zoom=1&edge=curl&source=gbs_api",
  "first_published": 2017,
  "pages": 281,
  "google_books_url": "https://play.google.com/store/books/details?id=92V7EAAAQBAJ&source=gbs_api",
  "language": "eng",
  "copyright_status": "public_domain",
  "subjects": [
    "Adventure stories",
    "Category: Novels",
    "Lotteries -- Fiction"
  ],
  "gutenberg_id": 13527,
  "gutenberg_url": "https://www.gutenberg.org/ebooks/13527",
  "gutenberg_read_url": "https://www.gutenberg.org/ebooks/13527.html.images"
}